geohashlite/__init__.py
geohashlite/geohash.py
geohashlite/geohash_shape.py
geohashlite-0.3.2.dist-info/LICENSE
geohashlite-0.3.2.dist-info/METADATA
geohashlite-0.3.2.dist-info/WHEEL
geohashlite-0.3.2.dist-info/top_level.txt
geohashlite-0.3.2.dist-info/RECORD
