Metadata-Version: 2.1
Name: geohashlite
Version: 0.3.2
Summary: A python library for interacting with geohash
Home-page: UNKNOWN
Author: Xuzhou Qin
Author-email: me@qinxuzhou.com
License: LICENSE
Platform: UNKNOWN
Requires-Dist: shapely
